license.md
setup.cfg
setup.py
Heb/Heb.py
Heb/__init__.py
Heb.egg-info/PKG-INFO
Heb.egg-info/SOURCES.txt
Heb.egg-info/dependency_links.txt
Heb.egg-info/top_level.txt