Metadata-Version: 2.1
Name: Heb
Version: 7.0.0
Summary: DIP lab
Author: NMIT
Author-email: string2025@gmail.com
License-File: license.md
